{"_ts": 1772012157.6415324, "payload": {"channel_id": "UCabsTV34JwALXKGMqHpvUiA", "channel_name": "VTV24", "description": "Kênh Youtube Chính Thức Của VTV Digital - Đài Truyền Hình Việt Nam\n\nVTV24 là đơn vị sản xuất các bản tin Tài chính kinh doanh & Chuyển động 24h với những thông tin thời sự được cập nhật nhanh chóng, chính xác nhất.\n\nĐồng hành cùng VTV24 tại:\nFanpage chính thức      : fb.com/tintucvtv24\nChuyên trang Tài Chính: fb.com/vtv24money\nZalo                                  : zalo.me/1571891271885013375\nYoutube Channel           : youtube.com/vtv24\nTiktok                               :tiktok.com/@vtv24news\nTwitter                              : https://twitter.com/vtvdigitalnews\n", "subscribers": 6860000, "total_views": 5661675216, "video_count": 54838, "published_at": "2016-02-17T07:33:02Z", "country": "VN"}}